classifierAgent/__init__.py
classifierAgent/classifierAgent.py
classifierAgent-1.1.1.dist-info/METADATA
classifierAgent-1.1.1.dist-info/WHEEL
classifierAgent-1.1.1.dist-info/entry_points.txt
classifierAgent-1.1.1.dist-info/top_level.txt
classifierAgent-1.1.1.dist-info/RECORD
