Metadata-Version: 2.1
Name: classifierAgent
Version: 1.1.1
Summary: A Python package for performing classification on datasets.
Home-page: https://github.com/adnankarol/classifierAgent
Author: Adnan Karol
Author-email: adnanmushtaq5@gmail.com
License: MIT
Keywords: machine learning,classification,random forest,xgboost,svm,logistic regression,naive bayes,knn,decision tree
Classifier: Programming Language :: Python :: 3
Classifier: License :: OSI Approved :: MIT License
Classifier: Operating System :: OS Independent
Requires-Python: >=3.10
Requires-Dist: pandas >=1.1.0
Requires-Dist: numpy >=1.18.0
Requires-Dist: scikit-learn >=0.24.0
Requires-Dist: joblib >=1.0.0
Requires-Dist: matplotlib >=3.3.0
Requires-Dist: seaborn >=0.11.0
Requires-Dist: termcolor >=1.1.0
